Metadata-Version: 1.1
Name: fsapi
Version: 0.0.8
Summary: Implementation of the Frontier Silicon API for Python
Home-page: https://github.com/zhelev/python-fsapi.git
Author: Krasimir Zhelev
Author-email: krasimir.zhelev@gmail.com
License: Apache License 2.0
Download-URL: https://github.com/zhelev/python-fsapi/archive/0.0.6.zip
Keywords: fsapi frontier silicon
Platform: any
Classifier: Intended Audience :: Developers
Classifier: License :: OSI Approved :: Apache Software License
Classifier: Operating System :: OS Independent
Classifier: Programming Language :: Python :: 3
Classifier: Programming Language :: Python :: 3.0
Classifier: Programming Language :: Python :: 3.1
Classifier: Programming Language :: Python :: 3.2
Classifier: Programming Language :: Python :: 3.3
Classifier: Programming Language :: Python :: 3.4
Classifier: Programming Language :: Python :: 3.5
Classifier: Programming Language :: Python :: 3.6
Classifier: Topic :: Software Development :: Libraries
